django_onerror/__init__.py
django_onerror/admin.py
django_onerror/models.py
django_onerror/tests.py
django_onerror/urls.py
django_onerror/views.py
django_onerror/migrations/0001_initial.py
django_onerror/migrations/0002_onerrorreportinfo_extra.py
django_onerror/migrations/0003_auto_20190317_0002.py
django_onerror/migrations/__init__.py
django_onerror-1.1.1.dist-info/METADATA
django_onerror-1.1.1.dist-info/WHEEL
django_onerror-1.1.1.dist-info/top_level.txt
django_onerror-1.1.1.dist-info/RECORD
