Metadata-Version: 2.1
Name: django-onerror
Version: 1.1.1
Summary: Django ``window.onerror`` Report
Home-page: https://github.com/django-xxx/django-onerror
Author: Hackathon
Author-email: kimi.huang@brightcells.com
Keywords: Django window.onerror Report
Classifier: Development Status :: 5 - Production/Stable
Classifier: Environment :: Web Environment
Classifier: Framework :: Django
Classifier: Intended Audience :: Developers
Classifier: Programming Language :: Python
Classifier: Topic :: Software Development :: Libraries :: Python Modules
Classifier: Topic :: Office/Business :: Financial :: Spreadsheet
Requires-Dist: django-admin (>=1.2.4)
Requires-Dist: django-response
Requires-Dist: django-six
